Metadata-Version: 2.1
Name: integrals
Version: 0.2
Summary: Numerical approximators to calculate the definit integral
Home-page: https://github.com/NullOsama/Integrals
Author: Osama Maharmeh
Author-email: maharmeh.osama98@gmail.com
License: UNKNOWN
Platform: UNKNOWN
Classifier: Programming Language :: Python :: 3
Classifier: License :: OSI Approved :: MIT License
Classifier: Operating System :: OS Independent
Requires-Python: >=3.6
